weavelet/__init__.py
weavelet/core.py
weavelet-0.0.1.dist-info/METADATA
weavelet-0.0.1.dist-info/WHEEL
weavelet-0.0.1.dist-info/RECORD
