Metadata-Version: 2.4
Name: weavelet
Version: 0.0.1
Summary: A library for managing function calls in specific order, to avoid code repeating. Similar to Apache Hamilton but simpler.
Project-URL: Homepage, https://github.com/marek/weavelet
Project-URL: Repository, https://github.com/marek/weavelet.git
Project-URL: Issues, https://github.com/marek/weavelet/issues
Author-email: Marek <marek@example.com>
License: MIT
Keywords: dag,dependency,function,orchestration,workflow
Classifier: Development Status :: 3 - Alpha
Classifier: Intended Audience :: Developers
Classifier: License :: OSI Approved :: MIT License
Classifier: Programming Language :: Python :: 3
Classifier: Programming Language :: Python :: 3.12
Classifier: Programming Language :: Python :: 3.13
Requires-Python: >=3.12
